ibeatles/__init__.py
ibeatles/__main__.py
ibeatles/_version.py
ibeatles/config.json
ibeatles/config_handler.py
ibeatles/ibeatles.py
ibeatles/about/__init__.py
ibeatles/about/about_launcher.py
ibeatles/add_element/__init__.py
ibeatles/add_element/add_element_editor.py
ibeatles/all_steps/__init__.py
ibeatles/all_steps/event_handler.py
ibeatles/all_steps/infos_launcher.py
ibeatles/all_steps/list_hkl_lambda_d0.py
ibeatles/all_steps/log_launcher.py
ibeatles/all_steps/material.py
ibeatles/app/__init__.py
ibeatles/app/cli.py
ibeatles/app/gui.py
ibeatles/app/models/__init__.py
ibeatles/app/models/normalization_settings_model.py
ibeatles/app/models/time_spectra_model.py
ibeatles/app/presenters/__init__.py
ibeatles/app/presenters/normalization_settings_presenter.py
ibeatles/app/presenters/time_spectra_presenter.py
ibeatles/app/ui/normalization_settings_view.py
ibeatles/app/ui/normalization_settings_view.ui
ibeatles/app/ui/time_spectra_view.py
ibeatles/app/ui/time_spectra_view.ui
ibeatles/app/utils/__init__.py
ibeatles/app/utils/ui_loader.py
ibeatles/binning/__init__.py
ibeatles/binning/binning_handler.py
ibeatles/binning/binning_launcher.py
ibeatles/core/__init__.py
ibeatles/core/config.py
ibeatles/core/material.py
ibeatles/core/fitting/__init__.py
ibeatles/core/fitting/binning.py
ibeatles/core/fitting/utils.py
ibeatles/core/fitting/kropff/__init__.py
ibeatles/core/fitting/kropff/fitting.py
ibeatles/core/fitting/kropff/models.py
ibeatles/core/io/__init__.py
ibeatles/core/io/data_loading.py
ibeatles/core/processing/__init__.py
ibeatles/core/processing/moving_average.py
ibeatles/core/processing/normalization.py
ibeatles/core/strain/__init__.py
ibeatles/core/strain/export.py
ibeatles/core/strain/mapping.py
ibeatles/core/strain/visualization.py
ibeatles/core/utils/__init__.py
ibeatles/fitting/__init__.py
ibeatles/fitting/display.py
ibeatles/fitting/event_handler.py
ibeatles/fitting/export.py
ibeatles/fitting/filling_table_handler.py
ibeatles/fitting/fitting_functions.py
ibeatles-1.1.5.dist-info/licenses/LICENSE
ibeatles-1.1.5.dist-info/METADATA
ibeatles-1.1.5.dist-info/WHEEL
ibeatles-1.1.5.dist-info/entry_points.txt
ibeatles-1.1.5.dist-info/top_level.txt
ibeatles-1.1.5.dist-info/RECORD
