Metadata-Version: 2.4
Name: ibeatles
Version: 1.1.5
Summary: Bragg edge strain mapping
Author-email: Jean Bilheux <bilheuxjm@ornl.gov>, Chen Zhang <zhangc@ornl.gov>
Maintainer-email: Jean Bilheux <bilheuxjm@ornl.gov>, Chen Zhang <zhangc@ornl.gov>
License: MIT
Project-URL: homepage, https://github.com/ornlneutronimaging/iBeatles
Project-URL: Bug Tracker, https://github.com/ornlneutronimaging/iBeatles/issues
Project-URL: Source Code, https://github.com/ornlneutronimaging/iBeatles
Keywords: Bragg Edge,neutron,imaging,strain mapping
Classifier: Development Status :: 4 - Beta
Classifier: Programming Language :: Python :: 3
Classifier: License :: OSI Approved :: MIT License
Classifier: Topic :: Scientific/Engineering :: Physics
Classifier: Intended Audience :: Science/Research
Requires-Python: <3.13,>=3.11
License-File: LICENSE
Requires-Dist: numpy
Requires-Dist: matplotlib
Requires-Dist: h5py
Requires-Dist: args
Requires-Dist: Pillow
Requires-Dist: astropy
Requires-Dist: scipy
Requires-Dist: lmfit
Requires-Dist: loguru
Requires-Dist: tqdm
Requires-Dist: tomli
Requires-Dist: pydantic
Requires-Dist: ipython
Requires-Dist: QtPy
Requires-Dist: PyQt5
Requires-Dist: pyqtgraph
Requires-Dist: neutronbraggedge<3,>=2.0.6
Requires-Dist: changepy<0.5,>=0.4.0
Requires-Dist: neunorm<2,>=1.6.12
Dynamic: license-file
